{
  "title": "Section Chief Shima Kōsaku",
  "description": "",
  "artist": "HIROKANE Kenshi",
  "author": "HIROKANE Kenshi",
  "cover": "https://i0.wp.com/hiwamatanoboru.com/wp-content/uploads/2021/09/Section_Chief_Shima_Kosaku_ch000_000a.png",
  "chapters": {
    "001": {
      "title": "Lipstick on Your Collar",
      "last_updated": "1758058786",
      "groups": {
        "Hi Wa Mata Noboru": "/proxy/api/imgchest/chapter/o24aj9ql34l"
      },
      "volume": "01"
    },
    "002": {
      "title": "I'm Getting Sentimental Over You",
      "last_updated": "1758058815",
      "groups": {
        "Hi Wa Mata Noboru": "/proxy/api/imgchest/chapter/dl7p8peb6yo"
      },
      "volume": "01"
    },
    "003": {
      "title": "Changing Partners",
      "last_updated": "1758058840",
      "groups": {
        "Hi Wa Mata Noboru": "/proxy/api/imgchest/chapter/5xy225ajjyl"
      },
      "volume": "01"
    },
    "004": {
      "title": "Mambo No. 5",
      "last_updated": "1758058867",
      "groups": {
        "Hi Wa Mata Noboru": "/proxy/api/imgchest/chapter/9rydr9mdw7k"
      },
      "volume": "01"
    },
    "005": {
      "title": "Don't Be That Way Part I",
      "last_updated": "1758058891",
      "groups": {
        "Hi Wa Mata Noboru": "/proxy/api/imgchest/chapter/qb4zn2e234j"
      },
      "volume": "01"
    },
    "006": {
      "title": "Don't Be That Way Part II",
      "last_updated": "1758058916",
      "groups": {
        "Hi Wa Mata Noboru": "/proxy/api/imgchest/chapter/dl7p8pep6yo"
      },
      "volume": "01"
    },
    "007": {
      "title": "Blue Christmas",
      "last_updated": "1758059012",
      "groups": {
        "Hi Wa Mata Noboru": "/proxy/api/imgchest/chapter/wl7lopgpp7x"
      },
      "volume": "01"
    },
    "008": {
      "title": "I Love New York",
      "last_updated": "1758059071",
      "groups": {
        "Hi Wa Mata Noboru": "/proxy/api/imgchest/chapter/m9yx3pra3yq"
      },
      "volume": "01"
    },
    "009": {
      "title": "On the Sunny Side of the Street",
      "last_updated": "1763364647",
      "groups": {
        "Hi Wa Mata Noboru": "/proxy/api/imgchest/chapter/pg73dn8doyr"
      },
      "volume": "02"
    },
    "010": {
      "title": "My Fair Lady",
      "last_updated": "1763364666",
      "groups": {
        "Hi Wa Mata Noboru": "/proxy/api/imgchest/chapter/xny8ed9ewyb"
      },
      "volume": "02"
    },
    "011": {
      "title": "Tuxedo Junction",
      "last_updated": "1763364687",
      "groups": {
        "Hi Wa Mata Noboru": "/proxy/api/imgchest/chapter/bp45mlnmvy5"
      },
      "volume": "02"
    },
    "012": {
      "title": "Moon River",
      "last_updated": "1763364714",
      "groups": {
        "Hi Wa Mata Noboru": "/proxy/api/imgchest/chapter/a8463j9324x"
      },
      "volume": "02"
    },
    "013": {
      "title": "It's a Sin to Tell a Lie",
      "last_updated": "1763364730",
      "groups": {
        "Hi Wa Mata Noboru": "/proxy/api/imgchest/chapter/92492r928yn"
      },
      "volume": "02"
    },
    "014": {
      "title": "New York State of Mind",
      "last_updated": "1763364747",
      "groups": {
        "Hi Wa Mata Noboru": "/proxy/api/imgchest/chapter/dl7pa26nj7o"
      },
      "volume": "02"
    },
    "015": {
      "title": "Autumn in New York",
      "last_updated": "1763364765",
      "groups": {
        "Hi Wa Mata Noboru": "/proxy/api/imgchest/chapter/vj4jea6m978"
      },
      "volume": "02"
    },
    "016": {
      "title": "Sentimental Journey",
      "last_updated": "1763364783",
      "groups": {
        "Hi Wa Mata Noboru": "/proxy/api/imgchest/chapter/wl7lav6woyx"
      },
      "volume": "02"
    },
    "017": {
      "title": "The Moon was Yellow",
      "last_updated": "1763364833",
      "groups": {
        "Hi Wa Mata Noboru": "/proxy/api/imgchest/chapter/vj4jea6me78"
      },
      "volume": "02"
    },
    "018": {
      "title": "You'd Be So Nice to Come Home To",
      "last_updated": "1763364863",
      "groups": {
        "Hi Wa Mata Noboru": "/proxy/api/imgchest/chapter/pg73dn8o3yr"
      },
      "volume": "03"
    },
    "019": {
      "title": "Temptation",
      "last_updated": "1763364882",
      "groups": {
        "Hi Wa Mata Noboru": "/proxy/api/imgchest/chapter/qb4z5zrpv4j"
      },
      "volume": "03"
    },
    "020": {
      "title": "Mournin'",
      "last_updated": "1763364902",
      "groups": {
        "Hi Wa Mata Noboru": "/proxy/api/imgchest/chapter/xny8ed96dyb"
      },
      "volume": "03"
    },
    "021": {
      "title": "How Insensitive",
      "last_updated": "1763364921",
      "groups": {
        "Hi Wa Mata Noboru": "/proxy/api/imgchest/chapter/bp45mlnogy5"
      },
      "volume": "03"
    },
    "022": {
      "title": "Viva Las Vegas",
      "last_updated": "1763364937",
      "groups": {
        "Hi Wa Mata Noboru": "/proxy/api/imgchest/chapter/o24a2rm6w7l"
      },
      "volume": "03"
    },
    "023": {
      "title": "Round Midnight",
      "last_updated": "1763364954",
      "groups": {
        "Hi Wa Mata Noboru": "/proxy/api/imgchest/chapter/a8463j9ov4x"
      },
      "volume": "03"
    },
    "024": {
      "title": "El Cóndor Pasa (If I Could)",
      "last_updated": "1763364970",
      "groups": {
        "Hi Wa Mata Noboru": "/proxy/api/imgchest/chapter/92492r9layn"
      },
      "volume": "03"
    },
    "025": {
      "title": "California Dream",
      "last_updated": "1763364987",
      "groups": {
        "Hi Wa Mata Noboru": "/proxy/api/imgchest/chapter/9p4nv96klyn"
      },
      "volume": "03"
    },
    "026": {
      "title": "I'll See You in My Dreams",
      "last_updated": "1763365003",
      "groups": {
        "Hi Wa Mata Noboru": "/proxy/api/imgchest/chapter/md7oanv59yp"
      },
      "volume": "03"
    },
    "027": {
      "title": "I Left My Heart in San Francisco",
      "last_updated": "1763365038",
      "groups": {
        "Hi Wa Mata Noboru": "/proxy/api/imgchest/chapter/na7ka6n5m48"
      },
      "volume": "03"
    },
    "028": {
      "title": "Don't Explain",
      "last_updated": "1763365087",
      "groups": {
        "Hi Wa Mata Noboru": "/proxy/api/imgchest/chapter/ej7max6vj7d"
      },
      "volume": "04"
    },
    "029": {
      "title": "Moonlight Serenade",
      "last_updated": "1763365114",
      "groups": {
        "Hi Wa Mata Noboru": "/proxy/api/imgchest/chapter/n87w93jqbyx"
      },
      "volume": "04"
    },
    "030": {
      "title": "Deep Purple",
      "last_updated": "1763365134",
      "groups": {
        "Hi Wa Mata Noboru": "/proxy/api/imgchest/chapter/qb4z5zrmv4j"
      },
      "volume": "04"
    },
    "031": {
      "title": "In A Sentimental Mood",
      "last_updated": "1763365153",
      "groups": {
        "Hi Wa Mata Noboru": "/proxy/api/imgchest/chapter/qe4gmg8pb4j"
      },
      "volume": "04"
    },
    "032": {
      "title": "Sophisticated Lady",
      "last_updated": "1763365176",
      "groups": {
        "Hi Wa Mata Noboru": "/proxy/api/imgchest/chapter/bp45mln6gy5"
      },
      "volume": "04"
    },
    "033": {
      "title": "It's All Right With Me",
      "last_updated": "1763365195",
      "groups": {
        "Hi Wa Mata Noboru": "/proxy/api/imgchest/chapter/o24a2rmnw7l"
      },
      "volume": "04"
    },
    "034": {
      "title": "Memories of You",
      "last_updated": "1763365214",
      "groups": {
        "Hi Wa Mata Noboru": "/proxy/api/imgchest/chapter/agyvxkllz78"
      },
      "volume": "04"
    },
    "035": {
      "title": "It's Only a Paper Moon",
      "last_updated": "1763365233",
      "groups": {
        "Hi Wa Mata Noboru": "/proxy/api/imgchest/chapter/9p4nv966lyn"
      },
      "volume": "04"
    },
    "036": {
      "title": "That's Plenty",
      "last_updated": "1763365279",
      "groups": {
        "Hi Wa Mata Noboru": "/proxy/api/imgchest/chapter/na7ka6nnm48"
      },
      "volume": "04"
    },
    "037": {
      "title": "The Sidewinder",
      "last_updated": "1763365314",
      "groups": {
        "Hi Wa Mata Noboru": "/proxy/api/imgchest/chapter/bp45mlnngy5"
      },
      "volume": "05"
    },
    "038": {
      "title": "Dancing in the Dark",
      "last_updated": "1763365335",
      "groups": {
        "Hi Wa Mata Noboru": "/proxy/api/imgchest/chapter/o24a2rmmw7l"
      },
      "volume": "05"
    },
    "039": {
      "title": "My Foolish Heart",
      "last_updated": "1763365356",
      "groups": {
        "Hi Wa Mata Noboru": "/proxy/api/imgchest/chapter/agyvxklgz78"
      },
      "volume": "05"
    },
    "040": {
      "title": "You Do Something To Me",
      "last_updated": "1763365374",
      "groups": {
        "Hi Wa Mata Noboru": "/proxy/api/imgchest/chapter/92492r9mayn"
      },
      "volume": "05"
    },
    "041": {
      "title": "Sleepy Time Gal",
      "last_updated": "1763365390",
      "groups": {
        "Hi Wa Mata Noboru": "/proxy/api/imgchest/chapter/9p4nv96qlyn"
      },
      "volume": "05"
    },
    "042": {
      "title": "Speak Low",
      "last_updated": "1763365406",
      "groups": {
        "Hi Wa Mata Noboru": "/proxy/api/imgchest/chapter/dl7pa26rk7o"
      },
      "volume": "05"
    },
    "043": {
      "title": "Speak Low II",
      "last_updated": "1763365422",
      "groups": {
        "Hi Wa Mata Noboru": "/proxy/api/imgchest/chapter/md7oanvd9yp"
      },
      "volume": "05"
    },
    "044": {
      "title": "Alone Together",
      "last_updated": "1763365440",
      "groups": {
        "Hi Wa Mata Noboru": "/proxy/api/imgchest/chapter/na7ka6n2m48"
      },
      "volume": "05"
    },
    "045": {
      "title": "Relationships are Strange Things (Marriages are Made in Heaven)",
      "last_updated": "1763365456",
      "groups": {
        "Hi Wa Mata Noboru": "/proxy/api/imgchest/chapter/vj4jea65e78"
      },
      "volume": "05"
    },
    "046": {
      "title": "April Love",
      "last_updated": "1763365491",
      "groups": {
        "Hi Wa Mata Noboru": "/proxy/api/imgchest/chapter/ljyqal6mk72"
      },
      "volume": "05"
    },
    "047": {
      "title": "I Can't Get Started",
      "last_updated": "1763365526",
      "groups": {
        "Hi Wa Mata Noboru": "/proxy/api/imgchest/chapter/6eyraj6364p"
      },
      "volume": "06"
    },
    "048": {
      "title": "I'll Be Seeing You",
      "last_updated": "1763365553",
      "groups": {
        "Hi Wa Mata Noboru": "/proxy/api/imgchest/chapter/n87w93j8byx"
      },
      "volume": "06"
    },
    "049": {
      "title": "I'm a Fool to Want You (Though Love is a Foolish Thing)",
      "last_updated": "1763365581",
      "groups": {
        "Hi Wa Mata Noboru": "/proxy/api/imgchest/chapter/lqyedezwk7d"
      },
      "volume": "06"
    },
    "050": {
      "title": "Cheek to Cheek",
      "last_updated": "1763365602",
      "groups": {
        "Hi Wa Mata Noboru": "/proxy/api/imgchest/chapter/xny8ed9rdyb"
      },
      "volume": "06"
    },
    "051": {
      "title": "I Can't Give You Anything but Love",
      "last_updated": "1763365624",
      "groups": {
        "Hi Wa Mata Noboru": "/proxy/api/imgchest/chapter/o24a2rmdw7l"
      },
      "volume": "06"
    },
    "052": {
      "title": "Then Man I Love I",
      "last_updated": "1763365641",
      "groups": {
        "Hi Wa Mata Noboru": "/proxy/api/imgchest/chapter/a8463j9qv4x"
      },
      "volume": "06"
    },
    "053": {
      "title": "Then Man I Love II",
      "last_updated": "1763365657",
      "groups": {
        "Hi Wa Mata Noboru": "/proxy/api/imgchest/chapter/m9yx9wqlkyq"
      },
      "volume": "06"
    },
    "054": {
      "title": "I've Got You Under my Skin",
      "last_updated": "1763365680",
      "groups": {
        "Hi Wa Mata Noboru": "/proxy/api/imgchest/chapter/92492r95ayn"
      },
      "volume": "06"
    },
    "055": {
      "title": "Close Your Eyes I",
      "last_updated": "1763365719",
      "groups": {
        "Hi Wa Mata Noboru": "/proxy/api/imgchest/chapter/ne7blm3ovy5"
      },
      "volume": "06"
    },
    "056": {
      "title": "Close Your Eyes II",
      "last_updated": "1763365749",
      "groups": {
        "Hi Wa Mata Noboru": "/proxy/api/imgchest/chapter/md7oanv39yp"
      },
      "volume": "07"
    },
    "057": {
      "title": "My Funny Valentine I",
      "last_updated": "1763365765",
      "groups": {
        "Hi Wa Mata Noboru": "/proxy/api/imgchest/chapter/5xy2q9gm8yl"
      },
      "volume": "07"
    },
    "058": {
      "title": "My Funny Valentine II",
      "last_updated": "1763365781",
      "groups": {
        "Hi Wa Mata Noboru": "/proxy/api/imgchest/chapter/vj4jea6je78"
      },
      "volume": "07"
    },
    "059": {
      "title": "Everything Must Change",
      "last_updated": "1763365804",
      "groups": {
        "Hi Wa Mata Noboru": "/proxy/api/imgchest/chapter/5xy2q9gmnyl"
      },
      "volume": "07"
    },
    "060": {
      "title": "What's New",
      "last_updated": "1763365826",
      "groups": {
        "Hi Wa Mata Noboru": "/proxy/api/imgchest/chapter/wl7lav6d6yx"
      },
      "volume": "07"
    },
    "061": {
      "title": "Cleopatra's Dream",
      "last_updated": "1763365848",
      "groups": {
        "Hi Wa Mata Noboru": "/proxy/api/imgchest/chapter/ljyqal6ee72"
      },
      "volume": "07"
    },
    "062": {
      "title": "Yesterday's",
      "last_updated": "1763365870",
      "groups": {
        "Hi Wa Mata Noboru": "/proxy/api/imgchest/chapter/9rydqweod4k"
      },
      "volume": "07"
    },
    "063": {
      "title": "Carnival Morning (Manhã De Carnaval)",
      "last_updated": "1763365892",
      "groups": {
        "Hi Wa Mata Noboru": "/proxy/api/imgchest/chapter/ej7max6rq7d"
      },
      "volume": "07"
    },
    "064": {
      "title": "These Foolish Things",
      "last_updated": "1763365941",
      "groups": {
        "Hi Wa Mata Noboru": "/proxy/api/imgchest/chapter/n87w93j23yx"
      },
      "volume": "07"
    },
    "065": {
      "title": "Misty",
      "last_updated": "1763365975",
      "groups": {
        "Hi Wa Mata Noboru": "/proxy/api/imgchest/chapter/lqyedezox7d"
      },
      "volume": "08"
    },
    "066": {
      "title": "My Sadness (Tristeza)",
      "last_updated": "1763365991",
      "groups": {
        "Hi Wa Mata Noboru": "/proxy/api/imgchest/chapter/qe4gmg8ko4j"
      },
      "volume": "08"
    },
    "067": {
      "title": "On a Slow Boat to China",
      "last_updated": "1763366009",
      "groups": {
        "Hi Wa Mata Noboru": "/proxy/api/imgchest/chapter/xny8ed9wpyb"
      },
      "volume": "08"
    },
    "068": {
      "title": "It's All Right With Me",
      "last_updated": "1763366033",
      "groups": {
        "Hi Wa Mata Noboru": "/proxy/api/imgchest/chapter/bp45mlnrxy5"
      },
      "volume": "08"
    },
    "069": {
      "title": "Anything Goes",
      "last_updated": "1763366055",
      "groups": {
        "Hi Wa Mata Noboru": "/proxy/api/imgchest/chapter/a8463j9mg4x"
      },
      "volume": "08"
    },
    "070": {
      "title": "Five Spot After Dark",
      "last_updated": "1763366076",
      "groups": {
        "Hi Wa Mata Noboru": "/proxy/api/imgchest/chapter/agyvxklbw78"
      },
      "volume": "08"
    },
    "071": {
      "title": "Jawa no Yoru wa Fukete (Java-The Night in Java Wears On)",
      "last_updated": "1763366093",
      "groups": {
        "Hi Wa Mata Noboru": "/proxy/api/imgchest/chapter/m9yx9wqbmyq"
      },
      "volume": "08"
    },
    "072": {
      "title": "Come Together",
      "last_updated": "1763366110",
      "groups": {
        "Hi Wa Mata Noboru": "/proxy/api/imgchest/chapter/9p4nv96awyn"
      },
      "volume": "08"
    },
    "073": {
      "title": "Moonglow",
      "last_updated": "1763366127",
      "groups": {
        "Hi Wa Mata Noboru": "/proxy/api/imgchest/chapter/ne7blm3jky5"
      },
      "volume": "08"
    },
    "074": {
      "title": "Goodbye",
      "last_updated": "1763366146",
      "groups": {
        "Hi Wa Mata Noboru": "/proxy/api/imgchest/chapter/na7ka6ngk48"
      },
      "volume": "08"
    },
    "075": {
      "title": "Stormy Weather",
      "last_updated": "1763366188",
      "groups": {
        "Hi Wa Mata Noboru": "/proxy/api/imgchest/chapter/5xy2q9gjnyl"
      },
      "volume": "08"
    },
    "076": {
      "title": "Invitation",
      "last_updated": "1763366216",
      "groups": {
        "Hi Wa Mata Noboru": "/proxy/api/imgchest/chapter/9rydqwedd4k"
      },
      "volume": "09"
    },
    "077": {
      "title": "Solitude",
      "last_updated": "1763366237",
      "groups": {
        "Hi Wa Mata Noboru": "/proxy/api/imgchest/chapter/n87w93jb3yx"
      },
      "volume": "09"
    },
    "078": {
      "title": "Fly With the WInd",
      "last_updated": "1763366254",
      "groups": {
        "Hi Wa Mata Noboru": "/proxy/api/imgchest/chapter/qb4z5zrbg4j"
      },
      "volume": "09"
    },
    "079": {
      "title": "You an the Night and the Music",
      "last_updated": "1763366268",
      "groups": {
        "Hi Wa Mata Noboru": "/proxy/api/imgchest/chapter/qe4gmg83o4j"
      },
      "volume": "09"
    },
    "080": {
      "title": "Unforgettable",
      "last_updated": "1763366287",
      "groups": {
        "Hi Wa Mata Noboru": "/proxy/api/imgchest/chapter/bp45mlnvxy5"
      },
      "volume": "09"
    },
    "081": {
      "title": "I Should Care",
      "last_updated": "1763366304",
      "groups": {
        "Hi Wa Mata Noboru": "/proxy/api/imgchest/chapter/a8463j9ng4x"
      },
      "volume": "09"
    },
    "082": {
      "title": "Nature Boy",
      "last_updated": "1763366321",
      "groups": {
        "Hi Wa Mata Noboru": "/proxy/api/imgchest/chapter/m9yx9wqpmyq"
      },
      "volume": "09"
    },
    "083": {
      "title": "My Dreams Are Getting Better All the Time",
      "last_updated": "1763366338",
      "groups": {
        "Hi Wa Mata Noboru": "/proxy/api/imgchest/chapter/92492r9nvyn"
      },
      "volume": "09"
    },
    "084": {
      "title": "The World is Waiting for the Sunrise",
      "last_updated": "1763366355",
      "groups": {
        "Hi Wa Mata Noboru": "/proxy/api/imgchest/chapter/9p4nv96owyn"
      },
      "volume": "09"
    },
    "085": {
      "title": "Left Alone",
      "last_updated": "1763366372",
      "groups": {
        "Hi Wa Mata Noboru": "/proxy/api/imgchest/chapter/ne7blm39ky5"
      },
      "volume": "09"
    },
    "087": {
      "title": "Yes and No",
      "last_updated": "1763366476",
      "groups": {
        "Hi Wa Mata Noboru": "/proxy/api/imgchest/chapter/ljyqal6pe72"
      },
      "volume": "10"
    },
    "088": {
      "title": "Double Rainbow",
      "last_updated": "1763366507",
      "groups": {
        "Hi Wa Mata Noboru": "/proxy/api/imgchest/chapter/9rydqwe9d4k"
      },
      "volume": "10"
    },
    "089": {
      "title": "Softly, as in a Morning Sunrise",
      "last_updated": "1763366524",
      "groups": {
        "Hi Wa Mata Noboru": "/proxy/api/imgchest/chapter/ej7max6pq7d"
      },
      "volume": "10"
    },
    "090": {
      "title": "Giant Steps",
      "last_updated": "1763366544",
      "groups": {
        "Hi Wa Mata Noboru": "/proxy/api/imgchest/chapter/n87w93jp3yx"
      },
      "volume": "10"
    },
    "091": {
      "title": "Stella by Starlight I",
      "last_updated": "1763366562",
      "groups": {
        "Hi Wa Mata Noboru": "/proxy/api/imgchest/chapter/qe4gmg89o4j"
      },
      "volume": "10"
    },
    "092": {
      "title": "Stella by Starlight II",
      "last_updated": "1763366579",
      "groups": {
        "Hi Wa Mata Noboru": "/proxy/api/imgchest/chapter/o24a2rmeg7l"
      },
      "volume": "10"
    },
    "093": {
      "title": "Anniversary Song",
      "last_updated": "1763366589",
      "groups": {
        "Hi Wa Mata Noboru": "/proxy/api/imgchest/chapter/agyvxkl8w78"
      },
      "volume": "10"
    },
    "094": {
      "title": "Dahil sa Iyo (Because of You)",
      "last_updated": "1763366606",
      "groups": {
        "Hi Wa Mata Noboru": "/proxy/api/imgchest/chapter/92492r9bvyn"
      },
      "volume": "10"
    },
    "095": {
      "title": "I Thought About You I",
      "last_updated": "1763366622",
      "groups": {
        "Hi Wa Mata Noboru": "/proxy/api/imgchest/chapter/ne7blm3zky5"
      },
      "volume": "10"
    },
    "096": {
      "title": "I Thought About You II",
      "last_updated": "1763366641",
      "groups": {
        "Hi Wa Mata Noboru": "/proxy/api/imgchest/chapter/dl7pa26m87o"
      },
      "volume": "10"
    },
    "097": {
      "title": "I Thought About You III",
      "last_updated": "1763366658",
      "groups": {
        "Hi Wa Mata Noboru": "/proxy/api/imgchest/chapter/md7oanvrayp"
      },
      "volume": "10"
    },
    "098": {
      "title": "Señor Blues",
      "last_updated": "1763366691",
      "groups": {
        "Hi Wa Mata Noboru": "/proxy/api/imgchest/chapter/5xy2q9gvnyl"
      },
      "volume": "10"
    },
    "099": {
      "title": "Stella by Starlight III",
      "last_updated": "1763366719",
      "groups": {
        "Hi Wa Mata Noboru": "/proxy/api/imgchest/chapter/wl7lav6j6yx"
      },
      "volume": "11"
    },
    "100": {
      "title": "Stella by Starlight IV",
      "last_updated": "1763366857",
      "groups": {
        "Hi Wa Mata Noboru": "/proxy/api/imgchest/chapter/9rydqwe8d4k"
      },
      "volume": "11"
    },
    "101": {
      "title": "Stella by Starlight V",
      "last_updated": "1763366874",
      "groups": {
        "Hi Wa Mata Noboru": "/proxy/api/imgchest/chapter/bp45mln9xy5"
      },
      "volume": "11"
    },
    "102": {
      "title": "Stella by Starlight VI",
      "last_updated": "1763366890",
      "groups": {
        "Hi Wa Mata Noboru": "/proxy/api/imgchest/chapter/o24a2rmbg7l"
      },
      "volume": "11"
    },
    "103": {
      "title": "But Not For Me",
      "last_updated": "1763366907",
      "groups": {
        "Hi Wa Mata Noboru": "/proxy/api/imgchest/chapter/a8463j92g4x"
      },
      "volume": "11"
    },
    "104": {
      "title": "Summer Time",
      "last_updated": "1763366923",
      "groups": {
        "Hi Wa Mata Noboru": "/proxy/api/imgchest/chapter/agyvxklow78"
      },
      "volume": "11"
    },
    "105": {
      "title": "I Kiss Your Hand, Madame",
      "last_updated": "1763366941",
      "groups": {
        "Hi Wa Mata Noboru": "/proxy/api/imgchest/chapter/m9yx9wqomyq"
      },
      "volume": "11"
    },
    "106": {
      "title": "You Don't Know What Love Is",
      "last_updated": "1763366970",
      "groups": {
        "Hi Wa Mata Noboru": "/proxy/api/imgchest/chapter/92492r9qvyn"
      },
      "volume": "11"
    },
    "107": {
      "title": "Whisper Not",
      "last_updated": "1763367001",
      "groups": {
        "Hi Wa Mata Noboru": "/proxy/api/imgchest/chapter/dl7pa26o87o"
      },
      "volume": "11"
    },
    "108": {
      "title": "Kiss of Fire",
      "last_updated": "1763367021",
      "groups": {
        "Hi Wa Mata Noboru": "/proxy/api/imgchest/chapter/na7ka6nbk48"
      },
      "volume": "11"
    },
    "109": {
      "title": "I'm Beginning to See the Light",
      "last_updated": "1763367063",
      "groups": {
        "Hi Wa Mata Noboru": "/proxy/api/imgchest/chapter/5xy2q9g6nyl"
      },
      "volume": "11"
    },
    "110": {
      "title": "Strangers in the Night",
      "last_updated": "1763367095",
      "groups": {
        "Hi Wa Mata Noboru": "/proxy/api/imgchest/chapter/ljyqal6oe72"
      },
      "volume": "12"
    },
    "111": {
      "title": "Royal Garden Blues",
      "last_updated": "1763367112",
      "groups": {
        "Hi Wa Mata Noboru": "/proxy/api/imgchest/chapter/wl7lav6bpyx"
      },
      "volume": "12"
    },
    "112": {
      "title": "I Got it Bad",
      "last_updated": "1763367128",
      "groups": {
        "Hi Wa Mata Noboru": "/proxy/api/imgchest/chapter/vj4jea6b278"
      },
      "volume": "12"
    },
    "113": {
      "title": "Hat and Beard",
      "last_updated": "1763367145",
      "groups": {
        "Hi Wa Mata Noboru": "/proxy/api/imgchest/chapter/9rydqwebw4k"
      },
      "volume": "12"
    },
    "114": {
      "title": "Les Liaisons Dangereuses (Dangerous Liasons Blues)",
      "last_updated": "1763367162",
      "groups": {
        "Hi Wa Mata Noboru": "/proxy/api/imgchest/chapter/6eyraj6oe4p"
      },
      "volume": "12"
    },
    "115": {
      "title": "Amen",
      "last_updated": "1763367181",
      "groups": {
        "Hi Wa Mata Noboru": "/proxy/api/imgchest/chapter/pg73dn8vzyr"
      },
      "volume": "12"
    },
    "116": {
      "title": "Lament",
      "last_updated": "1763367197",
      "groups": {
        "Hi Wa Mata Noboru": "/proxy/api/imgchest/chapter/n87w93j3zyx"
      },
      "volume": "12"
    },
    "117": {
      "title": "Don't Worry About Me",
      "last_updated": "1763367214",
      "groups": {
        "Hi Wa Mata Noboru": "/proxy/api/imgchest/chapter/lqyedeze37d"
      },
      "volume": "12"
    },
    "118": {
      "title": "It Never Entered My Mind",
      "last_updated": "1763367231",
      "groups": {
        "Hi Wa Mata Noboru": "/proxy/api/imgchest/chapter/qb4z5zrz34j"
      },
      "volume": "12"
    },
    "119": {
      "title": "Laura",
      "last_updated": "1763367256",
      "groups": {
        "Hi Wa Mata Noboru": "/proxy/api/imgchest/chapter/xny8ed9doyb"
      },
      "volume": "12"
    },
    "120": {
      "title": "Laura II",
      "last_updated": "1763367321",
      "groups": {
        "Hi Wa Mata Noboru": "/proxy/api/imgchest/chapter/o24a2rmr37l"
      },
      "volume": "12"
    },
    "121": {
      "title": "String of Pearls",
      "last_updated": "1763367351",
      "groups": {
        "Hi Wa Mata Noboru": "/proxy/api/imgchest/chapter/agyvxklk978"
      },
      "volume": "13"
    },
    "122": {
      "title": "At Last",
      "last_updated": "1763367368",
      "groups": {
        "Hi Wa Mata Noboru": "/proxy/api/imgchest/chapter/m9yx9wqw3yq"
      },
      "volume": "13"
    },
    "123": {
      "title": "True Love",
      "last_updated": "1763367385",
      "groups": {
        "Hi Wa Mata Noboru": "/proxy/api/imgchest/chapter/92492r9r2yn"
      },
      "volume": "13"
    },
    "124": {
      "title": "Just in Time",
      "last_updated": "1763367405",
      "groups": {
        "Hi Wa Mata Noboru": "/proxy/api/imgchest/chapter/dl7pa26267o"
      },
      "volume": "13"
    },
    "125": {
      "title": "It Don't Mean a Thing if it Aint' Got That Swing",
      "last_updated": "1763367425",
      "groups": {
        "Hi Wa Mata Noboru": "/proxy/api/imgchest/chapter/5xy2q9g9jyl"
      },
      "volume": "13"
    },
    "126": {
      "title": "Crazy Rhythm",
      "last_updated": "1763367442",
      "groups": {
        "Hi Wa Mata Noboru": "/proxy/api/imgchest/chapter/wl7lav6vpyx"
      },
      "volume": "13"
    },
    "127": {
      "title": "Shiny Stockings",
      "last_updated": "1763367459",
      "groups": {
        "Hi Wa Mata Noboru": "/proxy/api/imgchest/chapter/vj4jea6a278"
      },
      "volume": "13"
    },
    "128": {
      "title": "She is Funny That Way",
      "last_updated": "1763367476",
      "groups": {
        "Hi Wa Mata Noboru": "/proxy/api/imgchest/chapter/ljyqal6lo72"
      },
      "volume": "13"
    },
    "129": {
      "title": "I've Got a Crush On You",
      "last_updated": "1763367493",
      "groups": {
        "Hi Wa Mata Noboru": "/proxy/api/imgchest/chapter/6eyraj6je4p"
      },
      "volume": "13"
    },
    "130": {
      "title": "Deep Night",
      "last_updated": "1763367522",
      "groups": {
        "Hi Wa Mata Noboru": "/proxy/api/imgchest/chapter/ej7max6xb7d"
      },
      "volume": "13"
    },
    "131": {
      "title": "Why Don't You Do Right",
      "last_updated": "1763367591",
      "groups": {
        "Hi Wa Mata Noboru": "/proxy/api/imgchest/chapter/n87w93jazyx"
      },
      "volume": "13"
    },
    "132": {
      "title": "Mean to Me",
      "last_updated": "1763367619",
      "groups": {
        "Hi Wa Mata Noboru": "/proxy/api/imgchest/chapter/qb4z5zrx34j"
      },
      "volume": "14"
    },
    "133": {
      "title": "My Melancholy Baby",
      "last_updated": "1763367637",
      "groups": {
        "Hi Wa Mata Noboru": "/proxy/api/imgchest/chapter/xny8ed9aoyb"
      },
      "volume": "14"
    },
    "134": {
      "title": "You Took Advantage",
      "last_updated": "1763367654",
      "groups": {
        "Hi Wa Mata Noboru": "/proxy/api/imgchest/chapter/o24a2rm537l"
      },
      "volume": "14"
    },
    "135": {
      "title": "Bye Bye Blackbird",
      "last_updated": "1763367671",
      "groups": {
        "Hi Wa Mata Noboru": "/proxy/api/imgchest/chapter/a8463j98w4x"
      },
      "volume": "14"
    },
    "136": {
      "title": "Bye Bye Blackbird II",
      "last_updated": "1763367688",
      "groups": {
        "Hi Wa Mata Noboru": "/proxy/api/imgchest/chapter/agyvxkl5978"
      },
      "volume": "14"
    },
    "137": {
      "title": "Bye Bye Blackbird III",
      "last_updated": "1763367706",
      "groups": {
        "Hi Wa Mata Noboru": "/proxy/api/imgchest/chapter/m9yx9wq63yq"
      },
      "volume": "14"
    },
    "138": {
      "title": "Glad to be Unhappy",
      "last_updated": "1763367728",
      "groups": {
        "Hi Wa Mata Noboru": "/proxy/api/imgchest/chapter/92492r962yn"
      },
      "volume": "14"
    },
    "139": {
      "title": "You Stepped Out of a Dream",
      "last_updated": "1763367749",
      "groups": {
        "Hi Wa Mata Noboru": "/proxy/api/imgchest/chapter/9p4nv96rzyn"
      },
      "volume": "14"
    },
    "140": {
      "title": "Will You Still Be Mine",
      "last_updated": "1763367765",
      "groups": {
        "Hi Wa Mata Noboru": "/proxy/api/imgchest/chapter/ne7blm3any5"
      },
      "volume": "14"
    },
    "141": {
      "title": "What is This Thing Called Love",
      "last_updated": "1763367784",
      "groups": {
        "Hi Wa Mata Noboru": "/proxy/api/imgchest/chapter/dl7pa26367o"
      },
      "volume": "14"
    },
    "142": {
      "title": "Yes, Indeed!",
      "last_updated": "1763367852",
      "groups": {
        "Hi Wa Mata Noboru": "/proxy/api/imgchest/chapter/md7oanvmdyp"
      },
      "volume": "14"
    },
    "143": {
      "title": "In a Mellow Tone",
      "last_updated": "1763367874",
      "groups": {
        "Hi Wa Mata Noboru": "/proxy/api/imgchest/chapter/vj4jea6l278"
      },
      "volume": "15"
    },
    "144": {
      "title": "When Sunny Gets Blue",
      "last_updated": "1763367890",
      "groups": {
        "Hi Wa Mata Noboru": "/proxy/api/imgchest/chapter/9rydqwekw4k"
      },
      "volume": "15"
    },
    "145": {
      "title": "A Ghost of a Chance",
      "last_updated": "1763367908",
      "groups": {
        "Hi Wa Mata Noboru": "/proxy/api/imgchest/chapter/6eyraj6ee4p"
      },
      "volume": "15"
    },
    "146": {
      "title": "Reflection",
      "last_updated": "1763367926",
      "groups": {
        "Hi Wa Mata Noboru": "/proxy/api/imgchest/chapter/pg73dn8ezyr"
      },
      "volume": "15"
    },
    "147": {
      "title": "Full House",
      "last_updated": "1763367951",
      "groups": {
        "Hi Wa Mata Noboru": "/proxy/api/imgchest/chapter/lqyedez837d"
      },
      "volume": "15"
    },
    "148": {
      "title": "Hollywood Jump",
      "last_updated": "1763367967",
      "groups": {
        "Hi Wa Mata Noboru": "/proxy/api/imgchest/chapter/qb4z5zrg34j"
      },
      "volume": "15"
    },
    "149": {
      "title": "Our Love is Here to Stay",
      "last_updated": "1763367986",
      "groups": {
        "Hi Wa Mata Noboru": "/proxy/api/imgchest/chapter/qe4gmg8ar4j"
      },
      "volume": "15"
    },
    "150": {
      "title": "Blues in the Night",
      "last_updated": "1763368005",
      "groups": {
        "Hi Wa Mata Noboru": "/proxy/api/imgchest/chapter/xny8ed9goyb"
      },
      "volume": "15"
    },
    "151": {
      "title": "Prelude in E Minor",
      "last_updated": "1763368021",
      "groups": {
        "Hi Wa Mata Noboru": "/proxy/api/imgchest/chapter/o24a2rmw37l"
      },
      "volume": "15"
    },
    "152": {
      "title": "Calling Blues",
      "last_updated": "1763368038",
      "groups": {
        "Hi Wa Mata Noboru": "/proxy/api/imgchest/chapter/agyvxkl3978"
      },
      "volume": "15"
    },
    "153": {
      "title": "Mack the Knife",
      "last_updated": "1763368070",
      "groups": {
        "Hi Wa Mata Noboru": "/proxy/api/imgchest/chapter/m9yx9wqe3yq"
      },
      "volume": "15"
    },
    "154": {
      "title": "I Surrender Dear",
      "last_updated": "1763368093",
      "groups": {
        "Hi Wa Mata Noboru": "/proxy/api/imgchest/chapter/ne7blm3eny5"
      },
      "volume": "16"
    },
    "155": {
      "title": "Wrap Your Troubles in Dreams",
      "last_updated": "1763368112",
      "groups": {
        "Hi Wa Mata Noboru": "/proxy/api/imgchest/chapter/dl7pa26l67o"
      },
      "volume": "16"
    },
    "156": {
      "title": "God Bless the Child",
      "last_updated": "1763368135",
      "groups": {
        "Hi Wa Mata Noboru": "/proxy/api/imgchest/chapter/na7ka6n9q48"
      },
      "volume": "16"
    },
    "157": {
      "title": "The Gift",
      "last_updated": "1763368158",
      "groups": {
        "Hi Wa Mata Noboru": "/proxy/api/imgchest/chapter/5xy2q9grjyl"
      },
      "volume": "16"
    },
    "158": {
      "title": "Songs From the Heart",
      "last_updated": "1763368180",
      "groups": {
        "Hi Wa Mata Noboru": "/proxy/api/imgchest/chapter/vj4jea6x278"
      },
      "volume": "16"
    },
    "159": {
      "title": "Return to Forever",
      "last_updated": "1763368197",
      "groups": {
        "Hi Wa Mata Noboru": "/proxy/api/imgchest/chapter/ljyqal6jo72"
      },
      "volume": "16"
    },
    "160": {
      "title": "Recado Bossa Nova",
      "last_updated": "1763368214",
      "groups": {
        "Hi Wa Mata Noboru": "/proxy/api/imgchest/chapter/6eyraj6qe4p"
      },
      "volume": "16"
    },
    "161": {
      "title": "Easy Living",
      "last_updated": "1763368505",
      "groups": {
        "Hi Wa Mata Noboru": "/proxy/api/imgchest/chapter/ej7max6bb7d"
      },
      "volume": "16"
    },
    "162": {
      "title": "Strange Fruits",
      "last_updated": "1763368525",
      "groups": {
        "Hi Wa Mata Noboru": "/proxy/api/imgchest/chapter/92492r9o2yn"
      },
      "volume": "16"
    },
    "163": {
      "title": "Star Eyes",
      "last_updated": "1763368542",
      "groups": {
        "Hi Wa Mata Noboru": "/proxy/api/imgchest/chapter/ne7blm38ny5"
      },
      "volume": "16"
    },
    "164": {
      "title": "I Want to Talk About You",
      "last_updated": "1763368580",
      "groups": {
        "Hi Wa Mata Noboru": "/proxy/api/imgchest/chapter/md7oanv6dyp"
      },
      "volume": "16"
    },
    "165": {
      "title": "Indian Love Call",
      "last_updated": "1763368603",
      "groups": {
        "Hi Wa Mata Noboru": "/proxy/api/imgchest/chapter/na7ka6n3q48"
      },
      "volume": "17"
    },
    "166": {
      "title": "Me And My Shadow",
      "last_updated": "1763368620",
      "groups": {
        "Hi Wa Mata Noboru": "/proxy/api/imgchest/chapter/5xy2q9gwjyl"
      },
      "volume": "17"
    },
    "167": {
      "title": "The Song is Ended",
      "last_updated": "1763368637",
      "groups": {
        "Hi Wa Mata Noboru": "/proxy/api/imgchest/chapter/wl7lav6epyx"
      },
      "volume": "17"
    },
    "168": {
      "title": "Confirmation",
      "last_updated": "1763368654",
      "groups": {
        "Hi Wa Mata Noboru": "/proxy/api/imgchest/chapter/ljyqal6no72"
      },
      "volume": "17"
    },
    "169": {
      "title": "You Are the Top",
      "last_updated": "1763368669",
      "groups": {
        "Hi Wa Mata Noboru": "/proxy/api/imgchest/chapter/wl7lav6eqyx"
      },
      "volume": "17"
    },
    "170": {
      "title": "Some Day My Prince Will Come",
      "last_updated": "1763368687",
      "groups": {
        "Hi Wa Mata Noboru": "/proxy/api/imgchest/chapter/vj4jea6rx78"
      },
      "volume": "17"
    },
    "171": {
      "title": "You Go to My Head",
      "last_updated": "1763368705",
      "groups": {
        "Hi Wa Mata Noboru": "/proxy/api/imgchest/chapter/6eyraj3rg4p"
      },
      "volume": "17"
    },
    "172": {
      "title": "More Than You Know",
      "last_updated": "1763368731",
      "groups": {
        "Hi Wa Mata Noboru": "/proxy/api/imgchest/chapter/pg73dn2kjyr"
      },
      "volume": "17"
    },
    "173": {
      "title": "I Get a Kick Out of You",
      "last_updated": "1763368759",
      "groups": {
        "Hi Wa Mata Noboru": "/proxy/api/imgchest/chapter/qb4z5zl6d4j"
      },
      "volume": "17"
    },
    "174": {
      "title": "It Might as Well Be Spring",
      "last_updated": "1763368781",
      "groups": {
        "Hi Wa Mata Noboru": "/proxy/api/imgchest/chapter/bp45mljkqy5"
      },
      "volume": "17"
    },
    "175": {
      "title": "Give Me the Simple Life",
      "last_updated": "1763368816",
      "groups": {
        "Hi Wa Mata Noboru": "/proxy/api/imgchest/chapter/a8463jqro4x"
      },
      "volume": "17"
    },
    "086": {
      "title": "The Champ",
      "last_updated": "1772358083",
      "groups": {
        "Hi Wa Mata Noboru": "/proxy/api/imgchest/chapter/qb4zrkpod7j"
      },
      "volume": "09"
    }
  }
}